mlrun_pipelines/common/__init__.py
mlrun_pipelines/common/helpers.py
mlrun_pipelines/common/models.py
mlrun_pipelines/common/mounts.py
mlrun_pipelines/common/ops.py
mlrun_pipelines_kfp_common_experiment-0.2.1.dist-info/METADATA
mlrun_pipelines_kfp_common_experiment-0.2.1.dist-info/WHEEL
mlrun_pipelines_kfp_common_experiment-0.2.1.dist-info/top_level.txt
mlrun_pipelines_kfp_common_experiment-0.2.1.dist-info/RECORD
