Metadata-Version: 2.1
Name: mlrun-pipelines-kfp-common-experiment
Version: 0.2.1
Summary: MLRun Pipelines package for providing KFP 1.8 compatibility
Home-page: https://github.com/mlrun/mlrun
Author: Yaron Haviv
Author-email: yaronh@iguazio.com
License: Apache License 2.0
Keywords: mlrun,kfp
Requires-Python: >=3.9, <3.12
